my/__init__.py
my/client.py
sample_pypi-0.0.1.dist-info/DESCRIPTION.rst
sample_pypi-0.0.1.dist-info/METADATA
sample_pypi-0.0.1.dist-info/RECORD
sample_pypi-0.0.1.dist-info/WHEEL
sample_pypi-0.0.1.dist-info/metadata.json
sample_pypi-0.0.1.dist-info/top_level.txt
